inspectk/__init__.py
inspectk-0.9.0.dist-info/licenses/LICENSE
inspectk-0.9.0.dist-info/METADATA
inspectk-0.9.0.dist-info/WHEEL
inspectk-0.9.0.dist-info/top_level.txt
inspectk-0.9.0.dist-info/RECORD
