Metadata-Version: 2.4
Name: inspectk
Version: 0.9.0
Summary: import inspectk; inspectk.go() -- to examine variables on the call stack with a tk window
Author-email: Lion Kimbro <lionkimbro@gmail.com>
License-Expression: GPL-3.0-or-later
Project-URL: Homepage, https://github.com/LionKimbro/inspectk
Project-URL: Bug Tracker, https://github.com/LionKimbro/inspectk/issues
Classifier: Programming Language :: Python :: 3
Classifier: Operating System :: OS Independent
Requires-Python: >=3.7
License-File: LICENSE
Requires-Dist: liontk
Dynamic: license-file
